custom_flet_components/Carousal.py
custom_flet_components/Carousal2.py
custom_flet_components/CenteredWidget.py
custom_flet_components/Custom_API.py
custom_flet_components/Gallery_Viewer.py
custom_flet_components/Shimmer.py
custom_flet_components/ShimmerPro.py
custom_flet_components/__init__.py
custom_flet_components/cli.py
custom_flet_components/custom_router.py
custom_flet_components/helper.py
custom_flet_components/onboard.py
custom_flet_components-0.4.0.dist-info/LICENSE
custom_flet_components-0.4.0.dist-info/METADATA
custom_flet_components-0.4.0.dist-info/WHEEL
custom_flet_components-0.4.0.dist-info/entry_points.txt
custom_flet_components-0.4.0.dist-info/top_level.txt
custom_flet_components-0.4.0.dist-info/RECORD
