Metadata-Version: 2.1
Name: custom_flet_components
Version: 0.4.0
Summary: Custom Components For Flet Python
Author: Mudassir Farooq
Author-email: pktechmania21@gmail.com
License: MIT
License-File: LICENSE
Requires-Dist: flet >=0.28.3
